LICENSE
MANIFEST.in
README.md
setup.py
gmplnotebook/__init__.py
gmplnotebook/__main__.py
gmplnotebook/kernel.js
gmplnotebook/kernel.py
gmplnotebook.egg-info/PKG-INFO
gmplnotebook.egg-info/SOURCES.txt
gmplnotebook.egg-info/dependency_links.txt
gmplnotebook.egg-info/requires.txt
gmplnotebook.egg-info/top_level.txt