Metadata-Version: 1.0
Name: gmplnotebook
Version: 0.1.3
Summary: A GMPL/MathProg kernel+extension for Jupyter
Home-page: https://github.com/nelsonuhan/gmplnotebook
Author: Nelson Uhan
Author-email: nelson@uhan.me
License: GNU GPLv3
Platform: UNKNOWN
